{
  "openapi": "3.0.1",
  "info": {
    "title": "Recipe.API",
    "version": "1.0"
  },
  "paths": {
    "/WeatherForecast/GetWeatherForecast": {
      "get": {
        "tags": [
          "WeatherForecast"
        ],
        "parameters": [
          {
            "name": "orderBy",
            "in": "query",
            "schema": {
              "type": "string",
              "default": "id"
            }
          },
          {
            "name": "sortOrder",
            "in": "query",
            "schema": {
              "type": "string",
              "default": "ASC"
            }
          },
          {
            "name": "rpp",
            "in": "query",
            "schema": {
              "type": "integer",
              "format": "int32",
              "default": 10
            }
          },
          {
            "name": "pageNumber",
            "in": "query",
            "schema": {
              "type": "integer",
              "format": "int32",
              "default": 1
            }
          },
          {
            "name": "summary",
            "in": "query",
            "schema": {
              "type": "string",
              "default": ""
            }
          },
          {
            "name": "temperature",
            "in": "query",
            "schema": {
              "type": "integer",
              "format": "int32",
              "default": 11
            }
          }
        ],
        "responses": {
          "200": {
            "description": "OK"
          }
        }
      }
    },
    "/WeatherForecast/GetAnotherForecast/{id}": {
      "get": {
        "tags": [
          "WeatherForecast"
        ],
        "parameters": [
          {
            "name": "id",
            "in": "path",
            "required": true,
            "schema": {
              "type": "string",
              "format": "uuid"
            }
          }
        ],
        "responses": {
          "200": {
            "description": "OK"
          }
        }
      }
    },
    "/WeatherForecast": {
      "post": {
        "tags": [
          "WeatherForecast"
        ],
        "requestBody": {
          "content": {
            "application/json": {
              "schema": {
                "$ref": "#/components/schemas/WeatherForecast"
              }
            },
            "text/json": {
              "schema": {
                "$ref": "#/components/schemas/WeatherForecast"
              }
            },
            "application/*+json": {
              "schema": {
                "$ref": "#/components/schemas/WeatherForecast"
              }
            }
          }
        },
        "responses": {
          "200": {
            "description": "OK"
          }
        }
      }
    },
    "/WeatherForecast/{id}": {
      "put": {
        "tags": [
          "WeatherForecast"
        ],
        "parameters": [
          {
            "name": "id",
            "in": "path",
            "required": true,
            "schema": {
              "type": "string",
              "format": "uuid"
            }
          }
        ],
        "requestBody": {
          "content": {
            "application/json": {
              "schema": {
                "$ref": "#/components/schemas/WeatherForecast"
              }
            },
            "text/json": {
              "schema": {
                "$ref": "#/components/schemas/WeatherForecast"
              }
            },
            "application/*+json": {
              "schema": {
                "$ref": "#/components/schemas/WeatherForecast"
              }
            }
          }
        },
        "responses": {
          "200": {
            "description": "OK"
          }
        }
      },
      "delete": {
        "tags": [
          "WeatherForecast"
        ],
        "parameters": [
          {
            "name": "id",
            "in": "path",
            "required": true,
            "schema": {
              "type": "string",
              "format": "uuid"
            }
          }
        ],
        "responses": {
          "200": {
            "description": "OK"
          }
        }
      }
    }
  },
  "components": {
    "schemas": {
      "WeatherForecast": {
        "type": "object",
        "properties": {
          "id": {
            "type": "string",
            "format": "uuid"
          },
          "date": {
            "type": "string",
            "format": "date"
          },
          "temperatureC": {
            "type": "integer",
            "format": "int32"
          },
          "temperatureF": {
            "type": "integer",
            "format": "int32",
            "readOnly": true
          },
          "summary": {
            "type": "string",
            "nullable": true
          }
        },
        "additionalProperties": false
      }
    }
  }
}